{
"res":{
	"loding0000": {"x":0,"y":0,"w":32,"h":32},
	"loding0001": {"x":32,"y":0,"w":32,"h":32},
	"loding0002": {"x":64,"y":0,"w":32,"h":32},
	"loding0003": {"x":96,"y":0,"w":32,"h":32},
	"loding0004": {"x":0,"y":32,"w":32,"h":32},
	"loding0005": {"x":32,"y":32,"w":32,"h":32},
	"loding0006": {"x":64,"y":32,"w":32,"h":32},
	"loding0007": {"x":96,"y":32,"w":32,"h":32},
	"loding0008": {"x":0,"y":64,"w":32,"h":32},
	"loding0009": {"x":32,"y":64,"w":32,"h":32},
	"loding0010": {"x":64,"y":64,"w":32,"h":32},
	"loding0011": {"x":96,"y":64,"w":32,"h":32}
},
"frames": {
	"loding": {
		"totalFrame": 12,
		"childrenFrame": [
			{"res":"loding0000","x":0,"y":0},
			{"res":"loding0001","x":0,"y":0},
			{"res":"loding0002","x":0,"y":0},
			{"res":"loding0003","x":0,"y":0},
			{"res":"loding0004","x":0,"y":0},
			{"res":"loding0005","x":0,"y":0},
			{"res":"loding0006","x":0,"y":0},
			{"res":"loding0007","x":0,"y":0},
			{"res":"loding0008","x":0,"y":0},
			{"res":"loding0009","x":0,"y":0},
			{"res":"loding0010","x":0,"y":0},
			{"res":"loding0011","x":0,"y":0}
		]
	}
}
}